Workbook

Sheet 参数输入
A1: 【基础业务参数】
A2: 参数名称 | B2: 参数值 | C2: 单位 | D2: 备注
A3: 日均销量 | B3: 500 | C3: 件/天 | D3: 月均15000件
A4: 单批次发货量 | B4: 2000 | C4: 件/批 | D4: 建议2000-5000件
A5: 月度发货频次 | B5: 4 | C5: 次/月 | D5: 每周1次
A7: 【头程物流渠道参数】
A8: 渠道名称 | B8: 运输方式 | C8: 单价(元/kg) | D8: 单件重量(kg) | E8: 固定成本(元/票) | F8: 参考时效(天)
A9: 美西-海运 | B9: 海运 | C9: 12 | D9: 1.2 | E9: 800 | F9: 30
A10: 美西-空运 | B10: 空运 | C10: 32 | D10: 1.2 | E10: 300 | F10: 7
A11: 美西-铁运 | B11: 铁运 | C11: 18 | D11: 1.2 | E11: 500 | F11: 22
A12: 美东-海运 | B12: 海运 | C12: 14 | D12: 1.2 | E12: 800 | F12: 42
A13: 美东-空运 | B13: 空运 | C13: 35 | D13: 1.2 | E13: 300 | F13: 8
A14: 美东-铁运 | B14: 铁运 | C14: 20 | D14: 1.2 | E14: 500 | F14: 28
A15: 欧洲-海运 | B15: 海运 | C15: 16 | D15: 1.2 | E15: 1000 | F15: 45
A16: 欧洲-空运 | B16: 空运 | C16: 38 | D16: 1.2 | E16: 400 | F16: 7
A18: 【尾程物流渠道参数】
A19: 渠道名称 | B19: 服务商 | C19: 首重(kg) | D19: 首重价格(元) | E19: 续重单价(元/kg) | F19: 平均时效(天)
A20: 美西-标准 | B20: USPS | C20: 0.5 | D20: 35 | E20: 8 | F20: 5
A21: 美西-经济 | B21: FedEx | C21: 1 | D21: 42 | E21: 6 | F21: 7
A22: 美东-标准 | B22: USPS | C22: 0.5 | D22: 38 | E22: 9 | F22: 5
A23: 美东-经济 | B23: FedEx | C23: 1 | D23: 45 | E23: 7 | F23: 7
A24: 欧洲-标准 | B24: DPD | C24: 0.5 | D24: 40 | E24: 10 | F24: 4
A25: 欧洲-经济 | B25: UPS | C25: 1 | D25: 50 | E25: 9 | F25: 6
A27: 【成本分摊参数】
A28: 参数名称 | B28: 参数值 | C28: 单位
A29: 仓储费(元/件/月) | B29: 2 | C29: 元
A30: 操作费(元/件) | B30: 3 | C30: 元
A31: 管理费(元/件) | B31: 1.5 | C31: 元
A32: 资金成本率(年化) | B32: 8 | C32: %
A34: 【目标约束】
A35: 约束项 | B35: 目标值 | C35: 说明
A36: 时效上限(天) | B36: 15 | C36: 超过需评估
A37: 单件成本上限(元) | B37: 80 | C37: 超过需优化

Sheet 成本计算
A1: 【头程单件成本计算】
A2: 渠道 | B2: 运输方式 | C2: 单价(元/kg) | D2: 单件重量(kg) | E2: 单件运费(元) | F2: 固定成本分摊(元) | G2: 单件头程成本(元)
A3: 美西-海运 | B3: 海运 | C3: =参数输入!C9 | D3: =参数输入!D9 | E3: =C3*D3 | F3: =参数输入!E9/参数输入!$B$4 | G3: =E3+F3
A4: 美西-空运 | B4: 空运 | C4: =参数输入!C10 | D4: =参数输入!D10 | E4: =C4*D4 | F4: =参数输入!E10/参数输入!$B$4 | G4: =E4+F4
A5: 美西-铁运 | B5: 铁运 | C5: =参数输入!C11 | D5: =参数输入!D11 | E5: =C5*D5 | F5: =参数输入!E11/参数输入!$B$4 | G5: =E5+F5
A6: 美东-海运 | B6: 海运 | C6: =参数输入!C12 | D6: =参数输入!D12 | E6: =C6*D6 | F6: =参数输入!E12/参数输入!$B$4 | G6: =E6+F6
A7: 美东-空运 | B7: 空运 | C7: =参数输入!C13 | D7: =参数输入!D13 | E7: =C7*D7 | F7: =参数输入!E13/参数输入!$B$4 | G7: =E7+F7
A8: 美东-铁运 | B8: 铁运 | C8: =参数输入!C14 | D8: =参数输入!D14 | E8: =C8*D8 | F8: =参数输入!E14/参数输入!$B$4 | G8: =E8+F8
A9: 欧洲-海运 | B9: 海运 | C9: =参数输入!C15 | D9: =参数输入!D15 | E9: =C9*D9 | F9: =参数输入!E15/参数输入!$B$4 | G9: =E9+F9
A10: 欧洲-空运 | B10: 空运 | C10: =参数输入!C16 | D10: =参数输入!D16 | E10: =C10*D10 | F10: =参数输入!E16/参数输入!$B$4 | G10: =E10+F10
A11: 【尾程单件成本计算】
A12: 渠道 | B12: 服务商 | C12: 首重(kg) | D12: 首重价格(元) | E12: 续重单价(元/kg) | F12: 单件重量(kg) | G12: 单件尾程成本(元)
A13: 美西-标准 | B13: USPS | C13: =参数输入!C20 | D13: =参数输入!D20 | E13: =参数输入!E20 | F13: 1.2 | G13: =IF(F13<=C13,D13,D13+(F13-C13)*E13)
A14: 美西-经济 | B14: FedEx | C14: =参数输入!C21 | D14: =参数输入!D21 | E14: =参数输入!E21 | F14: 1.2 | G14: =IF(F14<=C14,D14,D14+(F14-C14)*E14)
A15: 美东-标准 | B15: USPS | C15: =参数输入!C22 | D15: =参数输入!D22 | E15: =参数输入!E22 | F15: 1.2 | G15: =IF(F15<=C15,D15,D15+(F15-C15)*E15)
A16: 美东-经济 | B16: FedEx | C16: =参数输入!C23 | D16: =参数输入!D23 | E16: =参数输入!E23 | F16: 1.2 | G16: =IF(F16<=C16,D16,D16+(F16-C16)*E16)
A17: 欧洲-标准 | B17: DPD | C17: =参数输入!C24 | D17: =参数输入!D24 | E17: =参数输入!E24 | F17: 1.2 | G17: =IF(F17<=C17,D17,D17+(F17-C17)*E17)
A18: 欧洲-经济 | B18: UPS | C18: =参数输入!C25 | D18: =参数输入!D25 | E18: =参数输入!E25 | F18: 1.2 | G18: =IF(F18<=C18,D18,D18+(F18-C18)*E18)
A19: 【总成本汇总】
A20: 计算项 | B20: 金额(元/件)
A21: 头程平均成本 | B21: =AVERAGE(G3:G10)
A22: 尾程平均成本 | B22: =AVERAGE(G13:G18)
A23: 仓储费 | B23: =参数输入!B29
A24: 操作费 | B24: =参数输入!B30
A25: 管理费 | B25: =参数输入!B31
A26: 资金成本 | B26: =参数输入!B29*参数输入!B32/100/12
A27: 单件总成本 | B27: =SUM(B21:B26)

Sheet 策略对比
A1: 【成本优先 vs 时效优先 策略对比】
A3: 策略类型 | B3: 推荐渠道组合 | C3: 头程成本(元) | D3: 尾程成本(元) | E3: 总成本(元) | F3: 平均时效(天) | G3: 适用场景
A4: 成本优先(美西) | B4: 美西-海运+美西-经济 | C4: =成本计算!G3 | D4: =成本计算!G14 | E4: =C4+D4 | F4: =参数输入!F9+参数输入!F21 | G4: 低价产品、不着急
A5: 平衡策略(美西) | B5: 美西-铁运+美西-标准 | C5: =成本计算!G5 | D5: =成本计算!G13 | E5: =C5+D5 | F5: =参数输入!F11+参数输入!F20 | G5: 常规产品、性价比
A6: 时效优先(美西) | B6: 美西-空运+美西-标准 | C6: =成本计算!G4 | D6: =成本计算!G13 | E6: =C6+D6 | F6: =参数输入!F10+参数输入!F20 | G6: 高价值、急用
A7: 成本优先(美东) | B7: 美东-海运+美东-经济 | C7: =成本计算!G6 | D7: =成本计算!G16 | E7: =C7+D7 | F7: =参数输入!F12+参数输入!F23 | G7: 美东低价产品
A8: 平衡策略(美东) | B8: 美东-铁运+美东-标准 | C8: =成本计算!G8 | D8: =成本计算!G15 | E8: =C8+D8 | F8: =参数输入!F14+参数输入!F22 | G8: 美东常规产品
A9: 时效优先(美东) | B9: 美东-空运+美东-标准 | C9: =成本计算!G7 | D9: =成本计算!G15 | E9: =C9+D9 | F9: =参数输入!F13+参数输入!F22 | G9: 美东高价值
A11: 【批量对成本的影响分析】
A13: 单批次发货量 | B13: 头程固定成本分摊(元/件) | C13: 比基准节省
A14: 500 | B14: =参数输入!$E$9/500 | C14: =ROUND(参数输入!$E$9/500-参数输入!$E$9/参数输入!$B$4,2)
A15: 1000 | B15: =参数输入!$E$9/1000 | C15: =ROUND(参数输入!$E$9/1000-参数输入!$E$9/参数输入!$B$4,2)
A16: 2000 | B16: =参数输入!$E$9/2000 | C16: =ROUND(参数输入!$E$9/2000-参数输入!$E$9/参数输入!$B$4,2)
A17: 5000 | B17: =参数输入!$E$9/5000 | C17: =ROUND(参数输入!$E$9/5000-参数输入!$E$9/参数输入!$B$4,2)
A19: 【策略推荐】
A20: 综合推荐 | B20: 平衡策略（铁运+标准） | C20: 性价比最高，大多数产品适用
A21: 成本敏感型 | B21: 海运+经济 | C21: 适合低毛利、不着急的产品
A22: 时效敏感型 | B22: 空运+标准 | C22: 适合高毛利、促销品、补急单

Sheet 敏感度分析
A1: 【运价波动敏感度分析】
A3: 运价变动幅度 | B3: 单件成本变化(元) | C3: 总成本变化(元) | D3: 建议
A4: 0.2 | B4: =参数输入!$C$9*参数输入!$D$9*0.2 | C4: =B4*参数输入!$B$3 | D4: 考虑切换更便宜渠道
A5: 0.1 | B5: =参数输入!$C$9*参数输入!$D$9*0.1 | C5: =B5*参数输入!$B$3 | D5: 监控成本，暂不调整
A6: -0.1 | B6: =参数输入!$C$9*参数输入!$D$9*-0.1 | C6: =B6*参数输入!$B$3 | D6: 有利，可增加发货量
A7: -0.2 | B7: =参数输入!$C$9*参数输入!$D$9*-0.2 | C7: =B7*参数输入!$B$3 | D7: 加大备货，锁定低价
A9: 【销量波动敏感度分析】
A11: 日均销量 | B11: 单批次发货量 | C11: 固定成本分摊(元) | D11: 单件总成本(元)
A12: =参数输入!$B$3*0.5 | B12: =参数输入!$B$4*0.5 | C12: =参数输入!$E$9/B12 | D12: =成本计算!$B$27-成本计算!$B$21+C12
A13: =参数输入!$B$3*0.8 | B13: =参数输入!$B$4*0.8 | C13: =参数输入!$E$9/B13 | D13: =成本计算!$B$27-成本计算!$B$21+C13
A14: =参数输入!$B$3*1.0 | B14: =参数输入!$B$4*1.0 | C14: =参数输入!$E$9/B14 | D14: =成本计算!$B$27-成本计算!$B$21+C14
A15: =参数输入!$B$3*1.2 | B15: =参数输入!$B$4*1.2 | C15: =参数输入!$E$9/B15 | D15: =成本计算!$B$27-成本计算!$B$21+C15
A16: =参数输入!$B$3*1.5 | B16: =参数输入!$B$4*1.5 | C16: =参数输入!$E$9/B16 | D16: =成本计算!$B$27-成本计算!$B$21+C16
A18: 【敏感性结论】
A19: 关键影响因素 | B19: 影响程度 | C19: 控制建议
A20: 运价波动 | B20: 高 | C20: 签订长约、多家比价
A21: 批量大小 | B21: 中 | C21: 合并发货、提高单批次量
A22: 销量波动 | B22: 中 | C22: 动态调整、设置安全库存

Sheet 策略说明
A1: 【物流成本策略模型使用说明】
A3: 一、三种核心策略
A5: 1. 成本优先策略
A6: - 渠道组合：海运 + 经济型尾程
A7: - 适用：低毛利产品、不紧急的补货
A8: - 优点：成本最低
A9: - 缺点：时效慢（30-45天）
A11: 2. 平衡策略（推荐）
A12: - 渠道组合：铁运 + 标准尾程
A13: - 适用：常规产品、大多数SKU
A14: - 优点：成本和时效平衡
A16: 3. 时效优先策略
... A32: 4. 使用【敏感度分析】Sheet评估风险

Sheet 注意点
A1: 【使用注意点】
A3: 一、数据输入注意事项
A5: ⚠️ 参数值必须是纯数字，不能带单位
A6: ⚠️ 单件重量(kg)和首重(kg)单位必须统一
A7: ⚠️ 产品单价需要根据实际产品填写
A9: 二、常见公式错误解决
A11: ❌ #REF! 错误
A12: → Sheet名称不是"参数输入"或"成本计算"
A13: → 检查底部标签名称
A15: ❌ #DIV/0! 错误
A16: → 单批次发货量=0
A17: → 检查参数输入!B5是否为0
... A34: 📅 每季度：复盘策略有效性
