Workbook

Sheet 参数输入
A1: 【基础业务参数】
A2: 参数名称 | B2: 参数值 | C2: 单位 | D2: 备注
A3: 日均销量 | B3: 100 | C3: 件/天 | D3: 过去30天平均值
A4: 销量标准差 | B4: 20 | C4: 件 | D4: 过去30天计算
A5: 产品单价 | B5: 50 | C5: 元/件 | D5: 产品成本价
A6: 毛利率 | B6: 30 | C6: % | D6: 售价=单价÷(1-毛利率)
A7: 资金成本率 | B7: 8 | C7: % | D7: 年化
A9: 【库存参数】
A10: 参数名称 | B10: 参数值 | C10: 单位 | D10: 备注
A11: 当前库存 | B11: 500 | C11: 件 | D11: 现有库存量
A12: 在途库存 | B12: 300 | C12: 件 | D12: 已发未到
A13: 安全库存天数 | B13: 14 | C13: 天 | D13: 业务设定
A14: 补货周期 | B14: 7 | C14: 天 | D14: 采购+物流天数
A15: 服务水平 | B15: 95 | C15: % | D15: 不缺货概率
A16: Z值 | B16: 1.65 | D16: 服务水平95%对应Z=1.65
A18: 【补货成本参数】
A19: 参数名称 | B19: 参数值 | C19: 单位 | D19: 备注
A20: 单次采购固定成本 | B20: 500 | C20: 元/次 | D20: 下单行政成本
A21: 单件持有成本率 | B21: 15 | C21: % | D21: 占产品单价比例
A22: 缺货损失率 | B22: 10 | C22: % | D22: 占产品单价比例
A24: 【库存阈值参数】
A25: 参数名称 | B25: 参数值 | C25: 单位 | D25: 备注
A26: 补货点预警(天) | B26: 3 | C26: 天 | D26: 低于此值建议补货
A27: 紧急补货预警(天) | B27: 1 | C27: 天 | D27: 低于此值紧急补货
A28: 目标库存天数 | B28: 30 | C28: 天 | D28: 目标覆盖天数

Sheet 补货计算
A1: 【安全库存计算】
A3: 计算项 | B3: 公式 | C3: 数值 | D3: 单位
A4: 日均销量 | B4: 日均销量（参数引用） | C4: =参数输入!B3 -> 100 | D4: 件/天
A5: 销量标准差 | B5: 销量标准差（参数引用） | C5: =参数输入!B4 -> 20 | D5: 件
A6: 服务水平Z值 | B6: 服务水平Z值（参数引用） | C6: =参数输入!B16 -> 1.65
A7: 补货周期 | B7: 补货周期（参数引用） | C7: =参数输入!B14 -> 7 | D7: 天
A8: 安全库存 | B8: Z值 × 标准差 × √补货周期 | C8: =参数输入!B16*参数输入!B4*SQRT(参数输入!B14) -> 87.309793 | D8: 件
A9: 补货点 | B9: 日均销量 × 补货周期 + 安全库存 | C9: =参数输入!B3*参数输入!B14+C8 -> 787.30979 | D9: 件
A10: 目标库存 | B10: 日均销量 × (补货周期 + 安全库存天数) + 安全库存 | C10: =参数输入!B3*(参数输入!B14+参数输入!B13)+C8 -> 2187.3098 | D10: 件
A12: 【当前库存状况】
A14: 计算项 | B14: 数值 | C14: 单位
A15: 当前库存 | B15: 当前库存（参数引用） | C15: =参数输入!B11 -> 500
A16: 在途库存 | B16: 在途库存（参数引用） | C16: =参数输入!B12 -> 300
A17: 有效库存 | B17: 当前库存 + 在途库存 | C17: =C15+C16 -> 800 | D17: 件
A18: 补货点 | B18: 补货点（引用R9） | C18: =C9 -> 787.30979
A19: 目标库存 | B19: 目标库存（引用R10） | C19: =C10 -> 2187.3098
A21: 【补货决策】
A23: 判断项 | B23: 条件 | C23: 结论
A24: 是否低于补货点 | B24: 是否低于补货点 | C24: =IF(C17<C9,"是","否") -> 否
A25: 是否低于目标库存 | B25: 是否低于目标库存 | C25: =IF(C17<C10,"是","否") -> 是
A26: 建议补货量 | B26: MAX(0, 目标库存 - 有效库存) | C26: =MAX(0,C10-C17) -> 1387.3098
A27: 预计可卖天数 | B27: 当前库存 ÷ 日均销量 | C27: =C15/参数输入!B3 -> 5
A29: 【补货预警级别】
A31: 预警级别 | B31: 触发条件 | C31: 当前状态
A32: 🟢 库存充足 | B32: 有效库存 > 目标库存 | C32: =IF(C17>C10,"🟢 充足","")
A33: 🟡 建议补货 | B33: 补货点 < 有效库存 ≤ 目标库存 | C33: =IF(AND(C17<=C10,C17>C9),"🟡 建议补货","") -> 🟡 建议补货
A34: 🔴 紧急补货 | B34: 有效库存 ≤ 补货点 | C34: =IF(C17<=C9,"🔴 紧急补货","")
A36: 【经济订货批量EOQ】
A38: 计算项 | B38: 公式 | C38: 数值 | D38: 单位
A39: 年需求量 | B39: 日均销量 × 365 | C39: =参数输入!B3*365 -> 36500 | D39: 件/年
A40: 单次采购固定成本 | B40: 单次采购固定成本（参数引用） | C40: =参数输入!B20 -> 500 | D40: 元/次
A41: 单件持有成本 | B41: 产品单价 × 持有成本率 | C41: =参数输入!B5*(参数输入!B21/100) -> 7.5 | D41: 元/件/年
A42: 经济订货批量EOQ | B42: SQRT(2 × 年需求 × 单次成本 ÷ 持有成本) | C42: =ROUND(SQRT(2*C39*C40/C41),0) -> 2206 | D42: 件/批
A44: 【总成本分析】
A46: 成本项 | B46: 公式 | C46: 数值 | D46: 元/件
A47: 采购成本 | B47: 产品单价 | C47: =参数输入!B5 -> 50
A48: 采购固定成本分摊 | B48: 单次成本 ÷ EOQ | C48: =C40/C42 -> 0.22665458
A49: 持有成本 | B49: 产品单价 × 持有成本率 ÷ 2 | C49: =参数输入!B5*(参数输入!B21/100)/2 -> 3.75
A50: 缺货成本 | B50: 产品单价 × 缺货损失率 × 缺货概率 | C50: =参数输入!B5*(参数输入!B22/100)*(1-参数输入!B16/100) -> 4.9175
A51: 【单件总补货成本】 | B51: 采购+固定+持有+缺货 | C51: =SUM(C47:C50) -> 58.894155

Sheet 策略对比
A1: 【补货策略对比】
A3: 策略名称 | B3: 安全库存天数 | C3: 补货周期(天) | D3: 安全库存(件) | E3: 补货点(件) | F3: EOQ(件) | G3: 平均库存(件) | H3: 适用场景
A4: 激进型 | B4: 7 | C4: 7 | D4: =参数输入!$B$16*参数输入!$B$4*SQRT(B4) -> 87.309793 | E4: =参数输入!$B$3*C4+D4 -> 787.30979 | F4: =ROUND(SQRT(2*参数输入!$B$3*365*参数输入!$B$20/(参数输入!$B$5*参数输入!$B$21/100)),0) -> 2206 | G4: =(F4/2)+D4 -> 1190.3098 | H4: 资金优先、快周转
A5: 平衡型 | B5: 14 | C5: 7 | D5: =参数输入!$B$16*参数输入!$B$4*SQRT(B5) -> 123.47469 | E5: =参数输入!$B$3*C5+D5 -> 823.47469 | F5: =ROUND(SQRT(2*参数输入!$B$3*365*参数输入!$B$20/(参数输入!$B$5*参数输入!$B$21/100)),0) -> 2206 | G5: =(F5/2)+D5 -> 1226.4747 | H5: 推荐：大部分产品
A6: 保守型 | B6: 21 | C6: 7 | D6: =参数输入!$B$16*参数输入!$B$4*SQRT(B6) -> 151.225 | E6: =参数输入!$B$3*C6+D6 -> 851.225 | F6: =ROUND(SQRT(2*参数输入!$B$3*365*参数输入!$B$20/(参数输入!$B$5*参数输入!$B$21/100)),0) -> 2206 | G6: =(F6/2)+D6 -> 1254.225 | H6: 避免断货、稳定优先
A8: 【策略对比分析】
A10: 对比项 | B10: 激进型 | C10: 平衡型 | D10: 保守型
A11: 安全库存(件) | B11: =D4 -> 87.309793 | C11: =D5 -> 123.47469 | D11: =D6 -> 151.225
A12: 补货点(件) | B12: =E4 -> 787.30979 | C12: =E5 -> 823.47469 | D12: =E6 -> 851.225
A13: 最大库存(件) | B13: =F4+参数输入!B12 -> 2506 | C13: =F5+参数输入!B12 -> 2506 | D13: =F6+参数输入!B12 -> 2506
A14: 年平均周转次数 | B14: =参数输入!B3*365/G4 -> 30.664286 | C14: =参数输入!B3*365/G5 -> 29.760092 | D14: =参数输入!B3*365/G6 -> 29.101637
A16: 【策略推荐】
A17: 条件 | B17: 推荐策略
A18: 毛利高、资金充足 | B18: 保守型（避免断货）
A19: 毛利中等、求稳 | B19: 平衡型（推荐）
A20: 毛利低、资金紧张 | B20: 激进型（快周转）
A21: 新品测款 | B21: 激进型（少备货）
A22: 爆款产品 | B22: 保守型（保证供应）

Sheet 敏感度分析
A1: 【日均销量波动分析】
A3: 销量变化 | B3: 日均销量 | C3: 安全库存 | D3: 补货点 | E3: EOQ | F3: 年周转次数
A4: -0.3 | B4: =参数输入!$B$3*0.7 -> 70 | C4: =参数输入!$B$16*参数输入!$B$4*SQRT(参数输入!$B$14) -> 87.309793 | D4: =B4*参数输入!$B$14+C4 -> 577.30979 | E4: =ROUND(SQRT(2*B4*365*参数输入!$B$20/(参数输入!$B$5*参数输入!$B$21/100)),0) -> 1846 | F4: =B4*365/参数输入!$B$11 -> 51.1
A5: -0.2 | B5: =参数输入!$B$3*0.8 -> 80 | C5: =参数输入!$B$16*参数输入!$B$4*SQRT(参数输入!$B$14) -> 87.309793 | D5: =B5*参数输入!$B$14+C5 -> 647.30979 | E5: =ROUND(SQRT(2*B5*365*参数输入!$B$20/(参数输入!$B$5*参数输入!$B$21/100)),0) -> 1973 | F5: =B5*365/参数输入!$B$11 -> 58.4
A6: 0 | B6: =参数输入!$B$3*1 -> 100 | C6: =参数输入!$B$16*参数输入!$B$4*SQRT(参数输入!$B$14) -> 87.309793 | D6: =B6*参数输入!$B$14+C6 -> 787.30979 | E6: =ROUND(SQRT(2*B6*365*参数输入!$B$20/(参数输入!$B$5*参数输入!$B$21/100)),0) -> 2206 | F6: =B6*365/参数输入!$B$11 -> 73
A7: 0.2 | B7: =参数输入!$B$3*1.2 -> 120 | C7: =参数输入!$B$16*参数输入!$B$4*SQRT(参数输入!$B$14) -> 87.309793 | D7: =B7*参数输入!$B$14+C7 -> 927.30979 | E7: =ROUND(SQRT(2*B7*365*参数输入!$B$20/(参数输入!$B$5*参数输入!$B$21/100)),0) -> 2417 | F7: =B7*365/参数输入!$B$11 -> 87.6
A8: 0.3 | B8: =参数输入!$B$3*1.3 -> 130 | C8: =参数输入!$B$16*参数输入!$B$4*SQRT(参数输入!$B$14) -> 87.309793 | D8: =B8*参数输入!$B$14+C8 -> 997.30979 | E8: =ROUND(SQRT(2*B8*365*参数输入!$B$20/(参数输入!$B$5*参数输入!$B$21/100)),0) -> 2515 | F8: =B8*365/参数输入!$B$11 -> 94.9
A10: 【补货周期波动分析】
A12: 补货周期变化 | B12: 补货周期(天) | C12: 安全库存 | D12: 补货点 | E12: 影响说明
A13: -0.3 | B13: =参数输入!$B$14*0.7 -> 4.9 | C13: =参数输入!$B$16*参数输入!$B$4*SQRT(B13) -> 73.048614 | D13: =参数输入!$B$3*B13+C13 -> 563.04861 | E13: 周期越短，库存越低
A14: -0.2 | B14: =参数输入!$B$14*0.8 -> 5.6 | C14: =参数输入!$B$16*参数输入!$B$4*SQRT(B14) -> 78.092253 | D14: =参数输入!$B$3*B14+C14 -> 638.09225 | E14: 周期越短，风险越高
A15: 0 | B15: =参数输入!$B$14*1 -> 7 | C15: =参数输入!$B$16*参数输入!$B$4*SQRT(B15) -> 87.309793 | D15: =参数输入!$B$3*B15+C15 -> 787.30979 | E15: 当前设置
A16: 0.2 | B16: =参数输入!$B$14*1.2 -> 8.4 | C16: =参数输入!$B$16*参数输入!$B$4*SQRT(B16) -> 95.643087 | D16: =参数输入!$B$3*B16+C16 -> 935.64309 | E16: 周期越长，库存越高
A17: 0.3 | B17: =参数输入!$B$14*1.3 -> 9.1 | C17: =参数输入!$B$16*参数输入!$B$4*SQRT(B17) -> 99.548481 | D17: =参数输入!$B$3*B17+C17 -> 1009.5485 | E17: 周期越长，资金占用多
A19: 【敏感性结论】
A20: 敏感因素 | B20: 影响方向 | C20: 控制建议
A21: 日均销量 | B21: 正相关 | C21: 每周更新销量数据
A22: 补货周期 | B22: 正相关 | C22: 优化供应链缩短周期
A23: 销量波动 | B23: 正相关 | C23: 波动大时增加安全库存
A24: 产品单价 | B24: 正相关 | C24: 高价产品要更谨慎

Sheet 使用说明
A1: 【补货策略模型使用说明】
A3: 一、核心计算公式
A5: 1. 安全库存 = Z值 × 标准差 × √补货周期
A6: - Z值：服务水平95%对应1.65
A7: - 标准差：销量波动程度
A8: - 补货周期：采购+物流天数
A10: 2. 补货点 = 日均销量 × 补货周期 + 安全库存
A11: - 库存低于此值，触发补货
A13: 3. 目标库存 = 日均销量 × (补货周期 + 安全库存天数) + 安全库存
A14: - 补货的目标量
A16: 4. 经济订货批量EOQ = √(2 × 年需求 × 单次采购成本 ÷ 持有成本)
A17: - 使总成本最低的订货量
... A81: 📅 每季度：调整安全库存参数
